LICENSE.txt
MANIFEST.in
README.rst
requirements.txt
setup.py
resumeos/ResumeOs.py
resumeos/__init__.py
resumeos/__main__.py
resumeos.egg-info/PKG-INFO
resumeos.egg-info/SOURCES.txt
resumeos.egg-info/dependency_links.txt
resumeos.egg-info/entry_points.txt
resumeos.egg-info/requires.txt
resumeos.egg-info/top_level.txt
resumeos/my-cool-os-template/Makefile
resumeos/my-cool-os-template/README.md
resumeos/my-cool-os-template/boot.asm
resumeos/my-cool-os-template/grub.cfg
resumeos/my-cool-os-template/linker.ld
resumeos/my-cool-os-template/multiboot_header.asm