Metadata-Version: 1.0
Name: resumeos
Version: 0.0.1
Summary: Easily bootstrap an OS project to fool HR departments and pad your resume.
Home-page: https://github.com/melonmanchan/ResumeOS
Author: Matti Jokitulppo
Author-email: melonmanchan@gmail.com
License: MIT
Keywords: OS,resume,filler,lazy
Platform: UNKNOWN
